{"nodes":[{"id":"readme_dogvision","label":"Dogvision Project","file_type":"document","source_file":"README.md","source_location":null,"source_url":null,"captured_at":null,"author":null,"contributor":null},{"id":"readme_quick_start","label":"Quick Start","file_type":"document","source_file":"README.md","source_location":null,"source_url":null,"captured_at":null,"author":null,"contributor":null},{"id":"plan_objective","label":"Real-time Dog Detection Objective","file_type":"document","source_file":"plan.md","source_location":"Section 1","source_url":null,"captured_at":null,"author":null,"contributor":null},{"id":"plan_hard_constraints","label":"Hard Constraints (dog-only, GPU-first)","file_type":"document","source_file":"plan.md","source_location":"Section 2","source_url":null,"captured_at":null,"author":null,"contributor":null},{"id":"plan_coco_class_16","label":"COCO Class 16 (dog)","file_type":"document","source_file":"plan.md","source_location":null,"source_url":null,"captured_at":null,"author":null,"contributor":null},{"id":"plan_target_environment","label":"Target Environment (WSL2, CUDA 12.x, Python 3.10)","file_type":"document","source_file":"plan.md","source_location":"Section 3","source_url":null,"captured_at":null,"author":null,"contributor":null},{"id":"plan_gpu_stack","label":"GPU Stack","file_type":"document","source_file":"plan.md","source_location":"Section 4","source_url":null,"captured_at":null,"author":null,"contributor":null},{"id":"plan_pytorch","label":"PyTorch (CUDA, FP16/AMP)","file_type":"document","source_file":"plan.md","source_location":null,"source_url":null,"captured_at":null,"author":null,"contributor":null},{"id":"plan_ultralytics_yolov8","label":"Ultralytics YOLOv8","file_type":"document","source_file":"plan.md","source_location":null,"source_url":null,"captured_at":null,"author":null,"contributor":null},{"id":"plan_tensorrt_fp16","label":"TensorRT FP16 Export","file_type":"document","source_file":"plan.md","source_location":null,"source_url":null,"captured_at":null,"author":null,"contributor":null},{"id":"plan_cupy","label":"CuPy Ring Buffer / Kernels","file_type":"document","source_file":"plan.md","source_location":null,"source_url":null,"captured_at":null,"author":null,"contributor":null},{"id":"plan_numba_cuda","label":"Numba CUDA","file_type":"document","source_file":"plan.md","source_location":null,"source_url":null,"captured_at":null,"author":null,"contributor":null},{"id":"plan_cudf","label":"cuDF (RAPIDS)","file_type":"document","source_file":"plan.md","source_location":null,"source_url":null,"captured_at":null,"author":null,"contributor":null},{"id":"plan_opencv","label":"OpenCV (cv2)","file_type":"document","source_file":"plan.md","source_location":null,"source_url":null,"captured_at":null,"author":null,"contributor":null},{"id":"plan_pyav_decord","label":"PyAV / decord decode","file_type":"document","source_file":"plan.md","source_location":null,"source_url":null,"captured_at":null,"author":null,"contributor":null},{"id":"plan_architecture","label":"Three-Thread Pipeline Architecture","file_type":"document","source_file":"plan.md","source_location":"Section 5","source_url":null,"captured_at":null,"author":null,"contributor":null},{"id":"plan_stage1_ingestion","label":"Stage 1 - Ingestion","file_type":"document","source_file":"plan.md","source_location":"Section 5.1","source_url":null,"captured_at":null,"author":null,"contributor":null},{"id":"plan_stage2_detection","label":"Stage 2 - Detection (YOLOv8)","file_type":"document","source_file":"plan.md","source_location":"Section 5.2","source_url":null,"captured_at":null,"author":null,"contributor":null},{"id":"plan_stage3_roi_features","label":"Stage 3 - GPU ROI Features (HSV histogram)","file_type":"document","source_file":"plan.md","source_location":"Section 5.3","source_url":null,"captured_at":null,"author":null,"contributor":null},{"id":"plan_stage4_bytetrack","label":"Stage 4 - ByteTrack Tracking","file_type":"document","source_file":"plan.md","source_location":"Section 5.4","source_url":null,"captured_at":null,"author":null,"contributor":null},{"id":"plan_stage5_cudf_analytics","label":"Stage 5 - cuDF Rolling Window Analytics","file_type":"document","source_file":"plan.md","source_location":"Section 5.5","source_url":null,"captured_at":null,"author":null,"contributor":null},{"id":"plan_stage6_output","label":"Stage 6 - Output (annotated video, Parquet, JSON)","file_type":"document","source_file":"plan.md","source_location":"Section 5.6","source_url":null,"captured_at":null,"author":null,"contributor":null},{"id":"plan_ring_buffer_rationale","label":"Rationale: CuPy Ring Buffer for O(1) Append","file_type":"document","source_file":"plan.md","source_location":"Section 5.5","source_url":null,"captured_at":null,"author":null,"contributor":null},{"id":"plan_drop_oldest_rationale","label":"Rationale: Drop-Oldest Queue Policy for Real-Time","file_type":"document","source_file":"plan.md","source_location":"Section 5.1","source_url":null,"captured_at":null,"author":null,"contributor":null},{"id":"plan_trt_fp16_rationale","label":"Rationale: TensorRT FP16 Primary, PyTorch FP16 Fallback","file_type":"document","source_file":"plan.md","source_location":"Section 4","source_url":null,"captured_at":null,"author":null,"contributor":null},{"id":"plan_performance_targets","label":"Performance Targets (>=25 FPS 1080p RTX 3060)","file_type":"document","source_file":"plan.md","source_location":"Section 10","source_url":null,"captured_at":null,"author":null,"contributor":null},{"id":"plan_benchmark","label":"CPU-vs-GPU Benchmark Deliverable","file_type":"document","source_file":"plan.md","source_location":"Section 8","source_url":null,"captured_at":null,"author":null,"contributor":null},{"id":"plan_out_of_scope","label":"Out of Scope (v1) - breed, pose, multi-class","file_type":"document","source_file":"plan.md","source_location":"Section 11","source_url":null,"captured_at":null,"author":null,"contributor":null},{"id":"plan_edge_cases","label":"Error / Edge Cases","file_type":"document","source_file":"plan.md","source_location":"Section 9","source_url":null,"captured_at":null,"author":null,"contributor":null},{"id":"plan_repo_layout","label":"Repo Layout (detection/tracking/analytics/pipeline/utils)","file_type":"document","source_file":"plan.md","source_location":"Section 6","source_url":null,"captured_at":null,"author":null,"contributor":null},{"id":"howto_environment","label":"Environment Setup (WSL2 + conda)","file_type":"document","source_file":"HOW_TO_TRAIN_AND_RUN.md","source_location":"Section 1","source_url":null,"captured_at":null,"author":null,"contributor":null},{"id":"howto_wsl2_rationale","label":"Rationale: WSL2 Required Because cuDF is Linux-only","file_type":"document","source_file":"HOW_TO_TRAIN_AND_RUN.md","source_location":"Section 1","source_url":null,"captured_at":null,"author":null,"contributor":null},{"id":"howto_run_demo","label":"Run the Demo (demo.py)","file_type":"document","source_file":"HOW_TO_TRAIN_AND_RUN.md","source_location":"Section 2","source_url":null,"captured_at":null,"author":null,"contributor":null},{"id":"howto_cli_flags","label":"CLI Flags (--source, --weights, --no-trt)","file_type":"document","source_file":"HOW_TO_TRAIN_AND_RUN.md","source_location":"Section 2.6","source_url":null,"captured_at":null,"author":null,"contributor":null},{"id":"howto_pipeline_diagram","label":"Pipeline Diagram (decode -> YOLOv8+ByteTrack -> CuPy/cuDF)","file_type":"document","source_file":"HOW_TO_TRAIN_AND_RUN.md","source_location":"Section 3","source_url":null,"captured_at":null,"author":null,"contributor":null},{"id":"howto_gpu_optimizations","label":"Key GPU Optimizations","file_type":"document","source_file":"HOW_TO_TRAIN_AND_RUN.md","source_location":"Section 3","source_url":null,"captured_at":null,"author":null,"contributor":null},{"id":"howto_benchmark","label":"Benchmark GPU vs CPU","file_type":"document","source_file":"HOW_TO_TRAIN_AND_RUN.md","source_location":"Section 4","source_url":null,"captured_at":null,"author":null,"contributor":null},{"id":"howto_finetune","label":"Fine-Tune YOLOv8 on Dogs","file_type":"document","source_file":"HOW_TO_TRAIN_AND_RUN.md","source_location":"Section 5","source_url":null,"captured_at":null,"author":null,"contributor":null},{"id":"howto_stanford_dogs","label":"Stanford Dogs Dataset","file_type":"document","source_file":"HOW_TO_TRAIN_AND_RUN.md","source_location":"Section 5.1","source_url":null,"captured_at":null,"author":null,"contributor":null},{"id":"howto_oxford_pet","label":"Oxford-IIIT Pet Dataset","file_type":"document","source_file":"HOW_TO_TRAIN_AND_RUN.md","source_location":"Section 5.1","source_url":null,"captured_at":null,"author":null,"contributor":null},{"id":"howto_open_images_v7","label":"Open Images V7","file_type":"document","source_file":"HOW_TO_TRAIN_AND_RUN.md","source_location":"Section 5.1","source_url":null,"captured_at":null,"author":null,"contributor":null},{"id":"howto_roboflow_cvat","label":"Roboflow / CVAT Labeling","file_type":"document","source_file":"HOW_TO_TRAIN_AND_RUN.md","source_location":"Section 5.1","source_url":null,"captured_at":null,"author":null,"contributor":null},{"id":"howto_yolo_format","label":"YOLO Dataset Format","file_type":"document","source_file":"HOW_TO_TRAIN_AND_RUN.md","source_location":"Section 5.2","source_url":null,"captured_at":null,"author":null,"contributor":null},{"id":"howto_config_yaml","label":"configs/default.yaml","file_type":"document","source_file":"HOW_TO_TRAIN_AND_RUN.md","source_location":"Section 6","source_url":null,"captured_at":null,"author":null,"contributor":null},{"id":"howto_troubleshooting","label":"Troubleshooting (TRT, cuDF, FPS, OOM)","file_type":"document","source_file":"HOW_TO_TRAIN_AND_RUN.md","source_location":"Section 7","source_url":null,"captured_at":null,"author":null,"contributor":null},{"id":"howto_botsort_alt","label":"BoTSORT alternative tracker","file_type":"document","source_file":"HOW_TO_TRAIN_AND_RUN.md","source_location":"Section 7","source_url":null,"captured_at":null,"author":null,"contributor":null},{"id":"req_onnxruntime","label":"ONNX Runtime (CPU baseline)","file_type":"document","source_file":"requirements.txt","source_location":null,"source_url":null,"captured_at":null,"author":null,"contributor":null},{"id":"req_pandas","label":"pandas (CPU baseline)","file_type":"document","source_file":"requirements.txt","source_location":null,"source_url":null,"captured_at":null,"author":null,"contributor":null},{"id":"req_pyarrow","label":"PyArrow (Parquet)","file_type":"document","source_file":"requirements.txt","source_location":null,"source_url":null,"captured_at":null,"author":null,"contributor":null},{"id":"req_rich","label":"Rich (console table)","file_type":"document","source_file":"requirements.txt","source_location":null,"source_url":null,"captured_at":null,"author":null,"contributor":null},{"id":"req_requirements","label":"pip requirements.txt","file_type":"document","source_file":"requirements.txt","source_location":null,"source_url":null,"captured_at":null,"author":null,"contributor":null}],"edges":[{"source":"readme_dogvision","target":"plan_objective","relation":"references","confidence":"EXTRACTED","confidence_score":1.0,"source_file":"README.md","source_location":null,"weight":1.0},{"source":"readme_dogvision","target":"howto_environment","relation":"references","confidence":"EXTRACTED","confidence_score":1.0,"source_file":"README.md","source_location":null,"weight":1.0},{"source":"readme_dogvision","target":"plan_ultralytics_yolov8","relation":"references","confidence":"EXTRACTED","confidence_score":1.0,"source_file":"README.md","source_location":null,"weight":1.0},{"source":"readme_dogvision","target":"plan_tensorrt_fp16","relation":"references","confidence":"EXTRACTED","confidence_score":1.0,"source_file":"README.md","source_location":null,"weight":1.0},{"source":"readme_dogvision","target":"plan_stage4_bytetrack","relation":"references","confidence":"EXTRACTED","confidence_score":1.0,"source_file":"README.md","source_location":null,"weight":1.0},{"source":"readme_dogvision","target":"plan_stage5_cudf_analytics","relation":"references","confidence":"EXTRACTED","confidence_score":1.0,"source_file":"README.md","source_location":null,"weight":1.0},{"source":"plan_objective","target":"plan_hard_constraints","relation":"conceptually_related_to","confidence":"EXTRACTED","confidence_score":1.0,"source_file":"plan.md","source_location":null,"weight":1.0},{"source":"plan_hard_constraints","target":"plan_coco_class_16","relation":"references","confidence":"EXTRACTED","confidence_score":1.0,"source_file":"plan.md","source_location":null,"weight":1.0},{"source":"plan_gpu_stack","target":"plan_pytorch","relation":"references","confidence":"EXTRACTED","confidence_score":1.0,"source_file":"plan.md","source_location":null,"weight":1.0},{"source":"plan_gpu_stack","target":"plan_ultralytics_yolov8","relation":"references","confidence":"EXTRACTED","confidence_score":1.0,"source_file":"plan.md","source_location":null,"weight":1.0},{"source":"plan_gpu_stack","target":"plan_tensorrt_fp16","relation":"references","confidence":"EXTRACTED","confidence_score":1.0,"source_file":"plan.md","source_location":null,"weight":1.0},{"source":"plan_gpu_stack","target":"plan_cupy","relation":"references","confidence":"EXTRACTED","confidence_score":1.0,"source_file":"plan.md","source_location":null,"weight":1.0},{"source":"plan_gpu_stack","target":"plan_numba_cuda","relation":"references","confidence":"EXTRACTED","confidence_score":1.0,"source_file":"plan.md","source_location":null,"weight":1.0},{"source":"plan_gpu_stack","target":"plan_cudf","relation":"references","confidence":"EXTRACTED","confidence_score":1.0,"source_file":"plan.md","source_location":null,"weight":1.0},{"source":"plan_gpu_stack","target":"plan_opencv","relation":"references","confidence":"EXTRACTED","confidence_score":1.0,"source_file":"plan.md","source_location":null,"weight":1.0},{"source":"plan_gpu_stack","target":"plan_pyav_decord","relation":"references","confidence":"EXTRACTED","confidence_score":1.0,"source_file":"plan.md","source_location":null,"weight":1.0},{"source":"plan_architecture","target":"plan_stage1_ingestion","relation":"references","confidence":"EXTRACTED","confidence_score":1.0,"source_file":"plan.md","source_location":null,"weight":1.0},{"source":"plan_architecture","target":"plan_stage2_detection","relation":"references","confidence":"EXTRACTED","confidence_score":1.0,"source_file":"plan.md","source_location":null,"weight":1.0},{"source":"plan_architecture","target":"plan_stage3_roi_features","relation":"references","confidence":"EXTRACTED","confidence_score":1.0,"source_file":"plan.md","source_location":null,"weight":1.0},{"source":"plan_architecture","target":"plan_stage4_bytetrack","relation":"references","confidence":"EXTRACTED","confidence_score":1.0,"source_file":"plan.md","source_location":null,"weight":1.0},{"source":"plan_architecture","target":"plan_stage5_cudf_analytics","relation":"references","confidence":"EXTRACTED","confidence_score":1.0,"source_file":"plan.md","source_location":null,"weight":1.0},{"source":"plan_architecture","target":"plan_stage6_output","relation":"references","confidence":"EXTRACTED","confidence_score":1.0,"source_file":"plan.md","source_location":null,"weight":1.0},{"source":"plan_stage1_ingestion","target":"plan_pyav_decord","relation":"references","confidence":"EXTRACTED","confidence_score":1.0,"source_file":"plan.md","source_location":null,"weight":1.0},{"source":"plan_stage2_detection","target":"plan_ultralytics_yolov8","relation":"references","confidence":"EXTRACTED","confidence_score":1.0,"source_file":"plan.md","source_location":null,"weight":1.0},{"source":"plan_stage2_detection","target":"plan_tensorrt_fp16","relation":"references","confidence":"EXTRACTED","confidence_score":1.0,"source_file":"plan.md","source_location":null,"weight":1.0},{"source":"plan_stage3_roi_features","target":"plan_cupy","relation":"references","confidence":"EXTRACTED","confidence_score":1.0,"source_file":"plan.md","source_location":null,"weight":1.0},{"source":"plan_stage5_cudf_analytics","target":"plan_cudf","relation":"references","confidence":"EXTRACTED","confidence_score":1.0,"source_file":"plan.md","source_location":null,"weight":1.0},{"source":"plan_stage5_cudf_analytics","target":"plan_cupy","relation":"shares_data_with","confidence":"EXTRACTED","confidence_score":1.0,"source_file":"plan.md","source_location":null,"weight":1.0},{"source":"plan_ring_buffer_rationale","target":"plan_stage5_cudf_analytics","relation":"rationale_for","confidence":"EXTRACTED","confidence_score":1.0,"source_file":"plan.md","source_location":null,"weight":1.0},{"source":"plan_drop_oldest_rationale","target":"plan_stage1_ingestion","relation":"rationale_for","confidence":"EXTRACTED","confidence_score":1.0,"source_file":"plan.md","source_location":null,"weight":1.0},{"source":"plan_trt_fp16_rationale","target":"plan_tensorrt_fp16","relation":"rationale_for","confidence":"EXTRACTED","confidence_score":1.0,"source_file":"plan.md","source_location":null,"weight":1.0},{"source":"plan_benchmark","target":"req_onnxruntime","relation":"references","confidence":"EXTRACTED","confidence_score":1.0,"source_file":"plan.md","source_location":null,"weight":1.0},{"source":"plan_benchmark","target":"req_pandas","relation":"references","confidence":"EXTRACTED","confidence_score":1.0,"source_file":"plan.md","source_location":null,"weight":1.0},{"source":"howto_environment","target":"howto_wsl2_rationale","relation":"conceptually_related_to","confidence":"EXTRACTED","confidence_score":1.0,"source_file":"HOW_TO_TRAIN_AND_RUN.md","source_location":null,"weight":1.0},{"source":"howto_wsl2_rationale","target":"plan_cudf","relation":"rationale_for","confidence":"EXTRACTED","confidence_score":1.0,"source_file":"HOW_TO_TRAIN_AND_RUN.md","source_location":null,"weight":1.0},{"source":"howto_pipeline_diagram","target":"plan_architecture","relation":"semantically_similar_to","confidence":"INFERRED","confidence_score":0.9,"source_file":"HOW_TO_TRAIN_AND_RUN.md","source_location":null,"weight":1.0},{"source":"howto_gpu_optimizations","target":"plan_tensorrt_fp16","relation":"references","confidence":"EXTRACTED","confidence_score":1.0,"source_file":"HOW_TO_TRAIN_AND_RUN.md","source_location":null,"weight":1.0},{"source":"howto_gpu_optimizations","target":"plan_cupy","relation":"references","confidence":"EXTRACTED","confidence_score":1.0,"source_file":"HOW_TO_TRAIN_AND_RUN.md","source_location":null,"weight":1.0},{"source":"howto_gpu_optimizations","target":"plan_cudf","relation":"references","confidence":"EXTRACTED","confidence_score":1.0,"source_file":"HOW_TO_TRAIN_AND_RUN.md","source_location":null,"weight":1.0},{"source":"howto_gpu_optimizations","target":"plan_stage4_bytetrack","relation":"references","confidence":"EXTRACTED","confidence_score":1.0,"source_file":"HOW_TO_TRAIN_AND_RUN.md","source_location":null,"weight":1.0},{"source":"howto_benchmark","target":"plan_benchmark","relation":"semantically_similar_to","confidence":"INFERRED","confidence_score":0.9,"source_file":"HOW_TO_TRAIN_AND_RUN.md","source_location":null,"weight":1.0},{"source":"howto_finetune","target":"howto_stanford_dogs","relation":"cites","confidence":"EXTRACTED","confidence_score":1.0,"source_file":"HOW_TO_TRAIN_AND_RUN.md","source_location":null,"weight":1.0},{"source":"howto_finetune","target":"howto_oxford_pet","relation":"cites","confidence":"EXTRACTED","confidence_score":1.0,"source_file":"HOW_TO_TRAIN_AND_RUN.md","source_location":null,"weight":1.0},{"source":"howto_finetune","target":"howto_open_images_v7","relation":"cites","confidence":"EXTRACTED","confidence_score":1.0,"source_file":"HOW_TO_TRAIN_AND_RUN.md","source_location":null,"weight":1.0},{"source":"howto_finetune","target":"howto_roboflow_cvat","relation":"cites","confidence":"EXTRACTED","confidence_score":1.0,"source_file":"HOW_TO_TRAIN_AND_RUN.md","source_location":null,"weight":1.0},{"source":"howto_finetune","target":"howto_yolo_format","relation":"references","confidence":"EXTRACTED","confidence_score":1.0,"source_file":"HOW_TO_TRAIN_AND_RUN.md","source_location":null,"weight":1.0},{"source":"howto_run_demo","target":"howto_cli_flags","relation":"references","confidence":"EXTRACTED","confidence_score":1.0,"source_file":"HOW_TO_TRAIN_AND_RUN.md","source_location":null,"weight":1.0},{"source":"howto_run_demo","target":"howto_config_yaml","relation":"references","confidence":"EXTRACTED","confidence_score":1.0,"source_file":"HOW_TO_TRAIN_AND_RUN.md","source_location":null,"weight":1.0},{"source":"howto_troubleshooting","target":"howto_botsort_alt","relation":"references","confidence":"EXTRACTED","confidence_score":1.0,"source_file":"HOW_TO_TRAIN_AND_RUN.md","source_location":null,"weight":1.0},{"source":"howto_botsort_alt","target":"plan_stage4_bytetrack","relation":"semantically_similar_to","confidence":"INFERRED","confidence_score":0.85,"source_file":"HOW_TO_TRAIN_AND_RUN.md","source_location":null,"weight":1.0},{"source":"req_requirements","target":"plan_ultralytics_yolov8","relation":"references","confidence":"EXTRACTED","confidence_score":1.0,"source_file":"requirements.txt","source_location":null,"weight":1.0},{"source":"req_requirements","target":"plan_pytorch","relation":"references","confidence":"EXTRACTED","confidence_score":1.0,"source_file":"requirements.txt","source_location":null,"weight":1.0},{"source":"req_requirements","target":"plan_opencv","relation":"references","confidence":"EXTRACTED","confidence_score":1.0,"source_file":"requirements.txt","source_location":null,"weight":1.0},{"source":"req_requirements","target":"plan_pyav_decord","relation":"references","confidence":"EXTRACTED","confidence_score":1.0,"source_file":"requirements.txt","source_location":null,"weight":1.0},{"source":"req_requirements","target":"plan_numba_cuda","relation":"references","confidence":"EXTRACTED","confidence_score":1.0,"source_file":"requirements.txt","source_location":null,"weight":1.0},{"source":"req_requirements","target":"plan_cupy","relation":"references","confidence":"EXTRACTED","confidence_score":1.0,"source_file":"requirements.txt","source_location":null,"weight":1.0},{"source":"req_requirements","target":"req_pyarrow","relation":"references","confidence":"EXTRACTED","confidence_score":1.0,"source_file":"requirements.txt","source_location":null,"weight":1.0},{"source":"req_requirements","target":"req_rich","relation":"references","confidence":"EXTRACTED","confidence_score":1.0,"source_file":"requirements.txt","source_location":null,"weight":1.0},{"source":"req_requirements","target":"req_onnxruntime","relation":"references","confidence":"EXTRACTED","confidence_score":1.0,"source_file":"requirements.txt","source_location":null,"weight":1.0},{"source":"req_requirements","target":"req_pandas","relation":"references","confidence":"EXTRACTED","confidence_score":1.0,"source_file":"requirements.txt","source_location":null,"weight":1.0},{"source":"plan_performance_targets","target":"plan_stage2_detection","relation":"conceptually_related_to","confidence":"EXTRACTED","confidence_score":1.0,"source_file":"plan.md","source_location":null,"weight":1.0},{"source":"plan_edge_cases","target":"plan_stage1_ingestion","relation":"conceptually_related_to","confidence":"EXTRACTED","confidence_score":1.0,"source_file":"plan.md","source_location":null,"weight":1.0},{"source":"plan_repo_layout","target":"plan_architecture","relation":"conceptually_related_to","confidence":"EXTRACTED","confidence_score":1.0,"source_file":"plan.md","source_location":null,"weight":1.0}],"hyperedges":[{"id":"hyper_three_thread_pipeline","label":"Three-Thread GPU Pipeline Flow","nodes":["plan_stage1_ingestion","plan_stage2_detection","plan_stage4_bytetrack","plan_stage5_cudf_analytics","plan_stage6_output"],"relation":"form","confidence":"EXTRACTED","confidence_score":1.0,"source_file":"plan.md"},{"id":"hyper_gpu_stack_pattern","label":"GPU-First Stack (PyTorch+YOLOv8+TRT+CuPy+cuDF)","nodes":["plan_pytorch","plan_ultralytics_yolov8","plan_tensorrt_fp16","plan_cupy","plan_cudf"],"relation":"implement","confidence":"EXTRACTED","confidence_score":1.0,"source_file":"plan.md"},{"id":"hyper_training_workflow","label":"YOLOv8 Fine-Tune Workflow (dataset -> YOLO format -> train -> TRT export)","nodes":["howto_stanford_dogs","howto_yolo_format","howto_finetune","plan_tensorrt_fp16"],"relation":"participate_in","confidence":"EXTRACTED","confidence_score":0.9,"source_file":"HOW_TO_TRAIN_AND_RUN.md"}],"input_tokens":0,"output_tokens":0}